matador/__init__.py
matador/battery/__init__.py
matador/battery/electrode.py
matador/calculators/__init__.py
matador/calculators/ase.py
matador/calculators/calculator.py
matador/calculators/castep.py
matador/calculators/quantum_espresso.py
matador/cli/__init__.py
matador/cli/cli.py
matador/cli/dispersion.py
matador/cli/run3.py
matador/compute/__init__.py
matador/compute/batch.py
matador/compute/compute.py
matador/compute/pbs.py
matador/compute/queueing.py
matador/compute/slurm.py
matador/config/__init__.py
matador/config/config.py
matador/config/example_mongod.conf
matador/config/matador.mplstyle
matador/config/matadorrc.yml
matador/config/quickstart.py
matador/config/settings.py
matador/config/vesta_elements.ini
matador/crystal/__init__.py
matador/crystal/crystal.py
matador/crystal/crystal_site.py
matador/crystal/elastic.py
matador/crystal/network.py
matador/data/__init__.py
matador/data/constants.py
matador/data/nouns
matador/data/periodic_table.py
matador/data/words
matador/data/atomic_scattering/__init__.py
matador/data/atomic_scattering/atomic_scattering_factors.dat
matador/data/atomic_scattering/atomic_scattering_factors_gsas.dat
matador/data/atomic_scattering/atomic_scattering_factors_gsas.py
matador/data/atomic_scattering/atomic_scattering_factors_raspa.py
matador/data/atomic_scattering/atomic_scattering_loaders.py
matador/data/magres/__init__.py
matador/data/magres/electric_quadrupole_moments.csv
matador/data/magres/electric_quadrupole_moments.py
matador/db/__init__.py
matador/db/changes.py
matador/db/connect.py
matador/db/importer.py
matador/db/refine.py
matador/export/__init__.py
matador/export/export.py
matador/export/utils.py
matador/fingerprints/__init__.py
matador/fingerprints/fingerprint.py
matador/fingerprints/pdf.py
matador/fingerprints/pxrd.py
matador/fingerprints/similarity.py
matador/hull/__init__.py
matador/hull/hull.py
matador/hull/hull_diff.py
matador/hull/hull_ensemble.py
matador/hull/hull_temperature.py
matador/hull/phase_diagram.py
matador_db-0.11.2.dist-info/licenses/LICENSE
matador_db-0.11.2.dist-info/METADATA
matador_db-0.11.2.dist-info/WHEEL
matador_db-0.11.2.dist-info/entry_points.txt
matador_db-0.11.2.dist-info/top_level.txt
matador_db-0.11.2.dist-info/RECORD
