Metadata-Version: 2.4
Name: matador-db
Version: 0.11.2
Summary: MATerial and Atomic Databases Of Refined structures.
Home-page: https://github.com/ml-evs/matador
Author: Matthew Evans
Author-email: matador@ml-evs.science
Maintainer: Matthew Evans
Maintainer-email: matador@ml-evs.science
License: MIT
Classifier: Development Status :: 4 - Beta
Classifier: Intended Audience :: Science/Research
Classifier: License :: OSI Approved :: MIT License
Classifier: Programming Language :: Python :: 3
Classifier: Programming Language :: Python :: 3.9
Classifier: Programming Language :: Python :: 3.10
Classifier: Topic :: Scientific/Engineering
Classifier: Topic :: Scientific/Engineering :: Chemistry
Classifier: Topic :: Scientific/Engineering :: Physics
Requires-Python: >=3.9
License-File: LICENSE
Requires-Dist: numpy<2,>=1.24
Requires-Dist: scipy~=1.13
Requires-Dist: spglib<3,>=1.16
Provides-Extra: all
Requires-Dist: pre-commit~=2.20; extra == "all"
Requires-Dist: sphinx~=5.2; extra == "all"
Requires-Dist: sphinx-argparse; extra == "all"
Requires-Dist: sphinx-rtd-theme; extra == "all"
Requires-Dist: ipykernel~=6.15; extra == "all"
Requires-Dist: nbsphinx~=0.8; extra == "all"
Requires-Dist: jinja2~=3.1.2; extra == "all"
Requires-Dist: pymatgen>=2022; extra == "all"
Requires-Dist: ase~=3.22; extra == "all"
Requires-Dist: ascii_graph~=1.5; extra == "all"
Requires-Dist: networkx~=2.6; extra == "all"
Requires-Dist: statsmodels>=0.11; extra == "all"
Requires-Dist: seaborn>=0.10; extra == "all"
Requires-Dist: requests~=2.28; extra == "all"
Requires-Dist: pytest~=7.1; extra == "all"
Requires-Dist: nbval~=0.9; extra == "all"
Requires-Dist: pytest-cov~=4.0; extra == "all"
Requires-Dist: coverage~=6.4; extra == "all"
Requires-Dist: codecov~=2.1; extra == "all"
Requires-Dist: mongomock~=4.1; extra == "all"
Requires-Dist: ase~=3.22; extra == "all"
Requires-Dist: nglview~=3.0; extra == "all"
Requires-Dist: numpy<2,>=1.24; extra == "all"
Requires-Dist: scipy~=1.13; extra == "all"
Requires-Dist: psutil~=5.9; extra == "all"
Requires-Dist: pyyaml~=6.0; extra == "all"
Requires-Dist: pymongo<4.11,~=4.0; extra == "all"
Requires-Dist: numba>=0.55; extra == "all"
Requires-Dist: tqdm~=4.62; extra == "all"
Requires-Dist: matplotlib<3.6,>=3.0; extra == "all"
Requires-Dist: seekpath~=2.0; extra == "all"
Requires-Dist: spglib<3,>=1.16; extra == "all"
Requires-Dist: python-ternary~=1.0; extra == "all"
Provides-Extra: dev
Requires-Dist: pre-commit~=2.20; extra == "dev"
Provides-Extra: docs
Requires-Dist: sphinx~=5.2; extra == "docs"
Requires-Dist: sphinx-argparse; extra == "docs"
Requires-Dist: sphinx-rtd-theme; extra == "docs"
Requires-Dist: ipykernel~=6.15; extra == "docs"
Requires-Dist: nbsphinx~=0.8; extra == "docs"
Requires-Dist: jinja2~=3.1.2; extra == "docs"
Provides-Extra: optional
Requires-Dist: pymatgen>=2022; extra == "optional"
Requires-Dist: ase~=3.22; extra == "optional"
Requires-Dist: ascii_graph~=1.5; extra == "optional"
Requires-Dist: networkx~=2.6; extra == "optional"
Requires-Dist: statsmodels>=0.11; extra == "optional"
Requires-Dist: seaborn>=0.10; extra == "optional"
Requires-Dist: requests~=2.28; extra == "optional"
Provides-Extra: test
Requires-Dist: pytest~=7.1; extra == "test"
Requires-Dist: nbval~=0.9; extra == "test"
Requires-Dist: pytest-cov~=4.0; extra == "test"
Requires-Dist: coverage~=6.4; extra == "test"
Requires-Dist: codecov~=2.1; extra == "test"
Requires-Dist: mongomock~=4.1; extra == "test"
Provides-Extra: viz
Requires-Dist: ase~=3.22; extra == "viz"
Requires-Dist: nglview~=3.0; extra == "viz"
Provides-Extra: legacy
Requires-Dist: numpy<2,>=1.24; extra == "legacy"
Requires-Dist: scipy~=1.13; extra == "legacy"
Requires-Dist: psutil~=5.9; extra == "legacy"
Requires-Dist: pyyaml~=6.0; extra == "legacy"
Requires-Dist: pymongo<4.11,~=4.0; extra == "legacy"
Requires-Dist: numba>=0.55; extra == "legacy"
Requires-Dist: tqdm~=4.62; extra == "legacy"
Requires-Dist: matplotlib<3.6,>=3.0; extra == "legacy"
Requires-Dist: seekpath~=2.0; extra == "legacy"
Requires-Dist: spglib<3,>=1.16; extra == "legacy"
Requires-Dist: python-ternary~=1.0; extra == "legacy"
Dynamic: author
Dynamic: author-email
Dynamic: classifier
Dynamic: description
Dynamic: home-page
Dynamic: license
Dynamic: license-file
Dynamic: maintainer
Dynamic: maintainer-email
Dynamic: provides-extra
Dynamic: requires-dist
Dynamic: requires-python
Dynamic: summary
